{
    "EntaMalOmk": {
        "Date Birth": {
            "Day": "20",
            "Month": "7",
            "Year": "1998"
        },
        "Email": "ahvlcbskacbasl",
        "Name": {
            "First": "Mohammed",
            "Last": "Amr"
        },
        "Password": "3'dr",
        "Phone": "55555555555555"
    },
    "Kimozzz": {
        "Date Birth": {
            "Day": "17",
            "Month": "4",
            "Year": "1998"
        },
        "Email": "kimo20122424as65a51c56c1a",
        "Name": {
            "First": "Kimo",
            "Last": "Saad"
        },
        "Password": "123123",
        "Phone": "acsacascascascas"
    },
    "Kimozzzzzzz": {
        "Date Birth": {
            "Day": "17",
            "Month": "4",
            "Year": "1998"
        },
        "Email": "kimo201224@gmail.com",
        "Name": {
            "First": "Kamal",
            "Last": "Saad"
        },
        "Password": "ban10ban",
        "Phone": "01091159295"
    },
    "Kombeez": {
        "Date Birth": {
            "Day": "17",
            "Month": "12",
            "Year": "2020"
        },
        "Email": "",
        "Name": {
            "First": "",
            "Last": ""
        },
        "Password": "",
        "Phone": ""
    },
    "bros": {
        "Date Birth": {
            "Day": "20",
            "Month": "4",
            "Year": "2018"
        },
        "Email": "bjbcjkasbcks",
        "Name": {
            "First": "kamal",
            "Last": "saad"
        },
        "Password": "12345",
        "Phone": "0101123486451"
    },
    "bros lee": {
        "Date Birth": {
            "Day": "20",
            "Month": "4",
            "Year": "2018"
        },
        "Email": "abdo3134564@gmail.com",
        "Name": {
            "First": "abdo",
            "Last": "ahmad"
        },
        "Password": "123456789",
        "Phone": "01143212327"
    },
    "kimo": {
        "Date Birth": {
            "Day": "3",
            "Month": "4",
            "Year": "2018"
        },
        "Email": "zaaza1233@gmail.com",
        "Name": {
            "First": "Mo'men",
            "Last": "Mostafa"
        },
        "Password": "123",
        "Phone": "000011"
    },
    "kkkkkkkkkkkkk": {
        "Date Birth": {
            "Day": "20",
            "Month": "4",
            "Year": "2018"
        },
        "Email": "",
        "Name": {
            "First": "",
            "Last": ""
        },
        "Password": "",
        "Phone": ""
    },
    "mo2": {
        "Date Birth": {
            "Day": "3",
            "Month": "4",
            "Year": "2018"
        },
        "Email": "zaaza1233@gmail.com",
        "Name": {
            "First": "Mo'men",
            "Last": "Mostafa"
        },
        "Password": "123",
        "Phone": "000011"
    },
    "new": {
        "Date Birth": {
            "Day": "20",
            "Month": "4",
            "Year": "2018"
        },
        "Email": "Kimo201224@gmail.com",
        "Name": {
            "First": "Kamal",
            "Last": "Saad"
        },
        "Password": "123123",
        "Phone": "01091159295"
    },
    "roony6": {
        "Date Birth": {
            "Day": "20",
            "Month": "4",
            "Year": "2018"
        },
        "Email": "Mosa1998@gmail.com",
        "Name": {
            "First": "Mohamed",
            "Last": "Mosa"
        },
        "Password": "55555",
        "Phone": "0111111111111111"
    }
}
